README.md
setup.cfg
setup.py
orbi_dnsmasq/__init__.py
orbi_dnsmasq/__main__.py
orbi_dnsmasq/orbi_dnsmasq.py
orbi_dnsmasq.egg-info/PKG-INFO
orbi_dnsmasq.egg-info/SOURCES.txt
orbi_dnsmasq.egg-info/dependency_links.txt
orbi_dnsmasq.egg-info/entry_points.txt
orbi_dnsmasq.egg-info/requires.txt
orbi_dnsmasq.egg-info/top_level.txt