Metadata-Version: 2.1
Name: orbi-dnsmasq
Version: 1.1.0
Summary: Use selenium and telnet to automate orbi router's dnsmasq
Home-page: https://github.com/Diego-Zulu/orbi-dnsmasq
Author: Diego-Zulu
License: MIT
Download-URL: https://github.com/Diego-Zulu/orbi-dnsmasq/archive/v1.1.0.tar.gz
Keywords: orbi,dnsmasq
Platform: UNKNOWN
Classifier: Development Status :: 4 - Beta
Classifier: Intended Audience :: Information Technology
Classifier: Topic :: Internet :: Name Service (DNS)
Classifier: License :: OSI Approved :: MIT License
Classifier: Programming Language :: Python
Classifier: Programming Language :: Python :: 2.7
Classifier: Programming Language :: Python :: 3.7
Classifier: Programming Language :: Python :: 3.8
Requires-Python: >=2.7
